pyobs_andor/__init__.py
pyobs_andor/andorcamera.py
pyobs_andor/andorzylacamera.py
pyobs_andor/atcore.py
pyobs_andor/libandor.pyx
pyobs_andor-0.1.4.dist-info/METADATA
pyobs_andor-0.1.4.dist-info/WHEEL
pyobs_andor-0.1.4.dist-info/RECORD
