Metadata-Version: 2.3
Name: pyobs-andor
Version: 0.1.4
Summary: pyobs module for Andor cameras
License: MIT
Author: Tim-Oliver Husser
Author-email: thusser@uni-goettingen.de
Requires-Python: >=3.10,<3.13
Classifier: License :: OSI Approved :: MIT License
Classifier: Programming Language :: Python :: 3
Classifier: Programming Language :: Python :: 3.10
Classifier: Programming Language :: Python :: 3.11
Classifier: Programming Language :: Python :: 3.12
